CheckingPyTest
