Metadata-Version: 1.0
Name: CheckingPyTest
Version: 15.0
Summary: Linear Algebra
Home-page: UNKNOWN
Author: UNKNOWN
Author-email: UNKNOWN
License: UNKNOWN
Platform: UNKNOWN
